mplcatppuccin/__init__.py
mplcatppuccin/colormaps.py
mplcatppuccin/palette.py
mplcatppuccin/plots.py
mplcatppuccin/data/frappe.mplstyle
mplcatppuccin/data/latte.mplstyle
mplcatppuccin/data/macchiato.mplstyle
mplcatppuccin/data/mocha.mplstyle
mplcatppuccin/data/palettes.json
catppuccin_matplotlib-0.5.dist-info/LICENSE
catppuccin_matplotlib-0.5.dist-info/METADATA
catppuccin_matplotlib-0.5.dist-info/WHEEL
catppuccin_matplotlib-0.5.dist-info/top_level.txt
catppuccin_matplotlib-0.5.dist-info/RECORD
