Metadata-Version: 2.1
Name: catppuccin-matplotlib
Version: 0.5
Summary: 📊 Soothing pastel theme for matplotlib
Author-email: Bram de Wilde <contact@bramdewilde.com>
License: MIT License
Project-URL: homepage, https://github.com/brambozz/matplotlib-catppuccin
License-File: LICENSE
Requires-Dist: matplotlib
